pygments_xslfo_formatter-1.1.1.dist-info/top_level.txt
pygments_xslfo_formatter-1.1.1.dist-info/DESCRIPTION.rst
pygments_xslfo_formatter-1.1.1.dist-info/metadata.json
pygments_xslfo_formatter-1.1.1.dist-info/WHEEL
pygments_xslfo_formatter-1.1.1.dist-info/entry_points.txt
pygments_xslfo_formatter-1.1.1.dist-info/METADATA
pygments_xslfo_formatter-1.1.1.dist-info/RECORD
pygments_xslfo_formatter/xslfo.py
pygments_xslfo_formatter/__init__.py
