Metadata-Version: 2.0
Name: pygments-xslfo-formatter
Version: 1.1.1
Summary: A pygments formatter that outputs <fo:inline> tags
Home-page: https://bitbucket.org/sratcliffe/pygments-xslfo-formatter
Author: Steve Ratcliffe
Author-email: sr@parabola.me.uk
License: MIT
Keywords: syntax highlighting xsl-fo
Platform: any
Classifier: Development Status :: 4 - Beta
Classifier: Intended Audience :: Developers
Classifier: Intended Audience :: End Users/Desktop
Classifier: License :: OSI Approved :: MIT License
Classifier: Programming Language :: Python :: 2
Classifier: Programming Language :: Python :: 2.7
Classifier: Programming Language :: Python :: 3
Classifier: Programming Language :: Python :: 3.3
Classifier: Programming Language :: Python :: 3.4
Classifier: Topic :: Text Processing :: Filters
Requires-Dist: Pygments
